README.txt
setup.py
pdcalc/__init__.py
pdcalc.egg-info/PKG-INFO
pdcalc.egg-info/SOURCES.txt
pdcalc.egg-info/dependency_links.txt
pdcalc.egg-info/entry_points.txt
pdcalc.egg-info/top_level.txt
pdcalc/pd/__init__.py
pdcalc/pd/ca.py
pdcalc/pd/uk.py
pdcalc/pd/us.py