Metadata-Version: 1.0
Name: pdcalc
Version: 0.7
Summary: Public Domain Calculators library and webapp.
Home-page: http://publicdomaincalculators.okfn.org/
Author: Open Knowledge Foundation
Author-email: info@okfn.org
License: MIT
Platform: UNKNOWN
